imglatex/__init__.py
imglatex/cli.py
imglatex/imglatex.py
imglatex-0.2.1.dist-info/AUTHORS.rst
imglatex-0.2.1.dist-info/LICENSE
imglatex-0.2.1.dist-info/METADATA
imglatex-0.2.1.dist-info/WHEEL
imglatex-0.2.1.dist-info/entry_points.txt
imglatex-0.2.1.dist-info/top_level.txt
imglatex-0.2.1.dist-info/RECORD
