Metadata-Version: 2.1
Name: imglatex
Version: 0.2.1
Summary: Turns a folder full of images into a LaTeX file that contains them as figures with captions.
Home-page: https://github.com/odarbelaeze/imglatex
Author: Oscar Arbelaez
Author-email: odarbelaeze@gmail.com
License: MIT license
Keywords: imglatex
Platform: UNKNOWN
Classifier: Development Status :: 2 - Pre-Alpha
Classifier: Intended Audience :: Developers
Classifier: License :: OSI Approved :: MIT License
Classifier: Natural Language :: English
Classifier: Programming Language :: Python :: 3
Classifier: Programming Language :: Python :: 3.6
Requires-Dist: Click (>=6.0)
Requires-Dist: Jinja2 (<3,>=2.10.1)
